pvcheck/argparser.py
pvcheck/csvformatter.py
pvcheck/executor.py
pvcheck/exporter.py
pvcheck/formatter.py
pvcheck/htmlformatter.py
pvcheck/i18n.py
pvcheck/interactiveformatter.py
pvcheck/jsonformatter.py
pvcheck/main.py
pvcheck/match.py
pvcheck/parser.py
pvcheck/pvcheck.py
pvcheck/testdata.py
pvcheck/valgrind.py
pvcheck/wdiff.py
pvcheck-0.1.6.dist-info/entry_points.txt
pvcheck-0.1.6.dist-info/LICENSE
pvcheck-0.1.6.dist-info/WHEEL
pvcheck-0.1.6.dist-info/METADATA
pvcheck-0.1.6.dist-info/RECORD
