Metadata-Version: 2.1
Name: pvcheck
Version: 0.1.6
Summary: Perform automatic tests of the output produced by command line programs
Keywords: testing
Author: Claudio Cusano
Author-email: claudio.cusano@unipv.it
Maintainer: Claudio Cusano
Maintainer-email: claudio.cusano@unipv.it
Requires-Python: >=3.8,<4.0
Classifier: Programming Language :: Python :: 3
Classifier: Programming Language :: Python :: 3.10
Classifier: Programming Language :: Python :: 3.8
Classifier: Programming Language :: Python :: 3.9
